CHANGELOG.md
LICENSE
Makefile
README.md
pyproject.toml
sequentia/__init__.py
sequentia/_internal/__init__.py
sequentia/_internal/_data.py
sequentia/_internal/_hmm/__init__.py
sequentia/_internal/_hmm/topologies.py
sequentia/_internal/_multiprocessing.py
sequentia/_internal/_sklearn.py
sequentia/_internal/_typing.py
sequentia/_internal/_validation.py
sequentia/datasets/__init__.py
sequentia/datasets/base.py
sequentia/datasets/data/__init__.py
sequentia/datasets/data/digits.npz
sequentia/datasets/data/gene_families.npz
sequentia/datasets/digits.py
sequentia/datasets/gene_families.py
sequentia/enums.py
sequentia/model_selection/__init__.py
sequentia/model_selection/_search.py
sequentia/model_selection/_search_successive_halving.py
sequentia/model_selection/_split.py
sequentia/model_selection/_validation.py
sequentia/models/__init__.py
sequentia/models/base.py
sequentia/models/hmm/__init__.py
sequentia/models/hmm/classifier.py
sequentia/models/hmm/variants/__init__.py
sequentia/models/hmm/variants/base.py
sequentia/models/hmm/variants/categorical.py
sequentia/models/hmm/variants/gaussian_mixture.py
sequentia/models/knn/__init__.py
sequentia/models/knn/base.py
sequentia/models/knn/classifier.py
sequentia/models/knn/regressor.py
sequentia/preprocessing/__init__.py
sequentia/preprocessing/transforms.py
sequentia/version.py
tasks.py
tox.ini
sequentia-2.6.0.dist-info/LICENSE
sequentia-2.6.0.dist-info/METADATA
sequentia-2.6.0.dist-info/WHEEL
sequentia-2.6.0.dist-info/RECORD
