Metadata-Version: 2.1
Name: sequentia
Version: 2.6.0
Summary: Scikit-Learn compatible HMM and DTW based sequence machine learning algorithms in Python.
Home-page: https://github.com/eonu/sequentia
License: MIT
Keywords: python,machine-learning,time-series,hmm,hidden-markov-models,dtw,dynamic-time-warping,knn,k-nearest-neighbors,sequence-classification,time-series-classification,multivariate-time-series,variable-length,classification-algorithms
Author: Edwin Onuonga
Author-email: ed@eonu.net
Maintainer: Edwin Onuonga
Maintainer-email: ed@eonu.net
Requires-Python: >=3.11,<4.0
Classifier: Development Status :: 5 - Production/Stable
Classifier: Environment :: Console
Classifier: Framework :: Pydantic :: 2
Classifier: Intended Audience :: Developers
Classifier: Intended Audience :: Information Technology
Classifier: Intended Audience :: Science/Research
Classifier: License :: OSI Approved :: MIT License
Classifier: Operating System :: OS Independent
Classifier: Programming Language :: Python
Classifier: Programming Language :: Python :: 3
Classifier: Programming Language :: Python :: 3.11
Classifier: Programming Language :: Python :: 3.12
Classifier: Programming Language :: Python :: 3 :: Only
Classifier: Programming Language :: Python :: 3.13
Classifier: Programming Language :: Python :: Implementation :: CPython
Classifier: Topic :: Scientific/Engineering
Classifier: Topic :: Scientific/Engineering :: Artificial Intelligence
Classifier: Topic :: Software Development :: Libraries :: Python Modules
Classifier: Typing :: Typed
Requires-Dist: dtaidistance (>=2.3.10,<3.0.0)
Requires-Dist: hmmlearn (>=0.2.8,<1)
Requires-Dist: joblib (>=1.2,<2.0)
Requires-Dist: numba (>=0.56,<1) ; python_version >= "3.11" and python_version < "3.13"
Requires-Dist: numba (>=0.61.0rc2) ; python_version >= "3.13"
Requires-Dist: numpy (>=1.19.5,<3)
Requires-Dist: pydantic (>=2,<3)
Requires-Dist: scikit-learn (>=1.4,<2.0)
Requires-Dist: scipy (>=1.6,<2.0)
Project-URL: Documentation, https://sequentia.readthedocs.io/en/latest
Project-URL: Repository, https://github.com/eonu/sequentia
